tool/__init__.py
tool/tool.py
tesla_admin-0.0.4.dist-info/METADATA
tesla_admin-0.0.4.dist-info/WHEEL
tesla_admin-0.0.4.dist-info/entry_points.txt
tesla_admin-0.0.4.dist-info/top_level.txt
tesla_admin-0.0.4.dist-info/RECORD
